{
    "data": {
        "discussQuestionTopicTags": [
            {
                "id": "123",
                "name": "c++",
                "slug": "c",
                "numTopics": 19,
                "__typename": "DiscussTopicTagNode"
            },
            {
                "id": "9254",
                "name": "slidingwindow",
                "slug": "slidingwindow",
                "numTopics": 12,
                "__typename": "DiscussTopicTagNode"
            },
            {
                "id": "200",
                "name": "cpp",
                "slug": "cpp",
                "numTopics": 10,
                "__typename": "DiscussTopicTagNode"
            },
            {
                "id": "135",
                "name": "java",
                "slug": "java",
                "numTopics": 10,
                "__typename": "DiscussTopicTagNode"
            },
            {
                "id": "34",
                "name": "python",
                "slug": "python",
                "numTopics": 9,
                "__typename": "DiscussTopicTagNode"
            },
            {
                "id": "6698",
                "name": "python3",
                "slug": "python3",
                "numTopics": 7,
                "__typename": "DiscussTopicTagNode"
            },
            {
                "id": "7955",
                "name": "dp",
                "slug": "dp",
                "numTopics": 6,
                "__typename": "DiscussTopicTagNode"
            },
            {
                "id": "415",
                "name": "easy",
                "slug": "easy",
                "numTopics": 5,
                "__typename": "DiscussTopicTagNode"
            },
            {
                "id": "6167",
                "name": "easy-understanding",
                "slug": "easy-understanding",
                "numTopics": 3,
                "__typename": "DiscussTopicTagNode"
            },
            {
                "id": "98",
                "name": "javascript",
                "slug": "javascript",
                "numTopics": 3,
                "__typename": "DiscussTopicTagNode"
            },
            {
                "id": "7112",
                "name": "sliding window",
                "slug": "sliding-window-2",
                "numTopics": 3,
                "__typename": "DiscussTopicTagNode"
            },
            {
                "id": "11145",
                "name": "doubt",
                "slug": "doubt",
                "numTopics": 2,
                "__typename": "DiscussTopicTagNode"
            },
            {
                "id": "7219",
                "name": "easytounderstand",
                "slug": "easytounderstand",
                "numTopics": 2,
                "__typename": "DiscussTopicTagNode"
            },
            {
                "id": "99",
                "name": "greedy",
                "slug": "greedy",
                "numTopics": 2,
                "__typename": "DiscussTopicTagNode"
            },
            {
                "id": "14",
                "name": "java-solution",
                "slug": "java-solution",
                "numTopics": 2,
                "__typename": "DiscussTopicTagNode"
            },
            {
                "id": "346",
                "name": "swift",
                "slug": "swift",
                "numTopics": 2,
                "__typename": "DiscussTopicTagNode"
            },
            {
                "id": "11779",
                "name": "#easy-understanding",
                "slug": "easy-understanding-3",
                "numTopics": 1,
                "__typename": "DiscussTopicTagNode"
            },
            {
                "id": "8074",
                "name": "#javascript",
                "slug": "javascript-2",
                "numTopics": 1,
                "__typename": "DiscussTopicTagNode"
            },
            {
                "id": "8046",
                "name": "#python",
                "slug": "python-2",
                "numTopics": 1,
                "__typename": "DiscussTopicTagNode"
            },
            {
                "id": "8964",
                "name": "100 space",
                "slug": "100-space",
                "numTopics": 1,
                "__typename": "DiscussTopicTagNode"
            },
            {
                "id": "8967",
                "name": "100 speed",
                "slug": "100-speed",
                "numTopics": 1,
                "__typename": "DiscussTopicTagNode"
            },
            {
                "id": "5996",
                "name": "2 pointer",
                "slug": "2-pointer",
                "numTopics": 1,
                "__typename": "DiscussTopicTagNode"
            },
            {
                "id": "7434",
                "name": "brute force",
                "slug": "brute-force-2",
                "numTopics": 1,
                "__typename": "DiscussTopicTagNode"
            },
            {
                "id": "6404",
                "name": "clean code",
                "slug": "clean-code",
                "numTopics": 1,
                "__typename": "DiscussTopicTagNode"
            },
            {
                "id": "6350",
                "name": "code with explanation",
                "slug": "code-with-explanation",
                "numTopics": 1,
                "__typename": "DiscussTopicTagNode"
            },
            {
                "id": "6481",
                "name": "concise",
                "slug": "concise",
                "numTopics": 1,
                "__typename": "DiscussTopicTagNode"
            },
            {
                "id": "7980",
                "name": "counter",
                "slug": "counter",
                "numTopics": 1,
                "__typename": "DiscussTopicTagNode"
            },
            {
                "id": "11992",
                "name": "cyclic replacements",
                "slug": "cyclic-replacements",
                "numTopics": 1,
                "__typename": "DiscussTopicTagNode"
            },
            {
                "id": "8713",
                "name": "detailed explanation",
                "slug": "detailed-explanation",
                "numTopics": 1,
                "__typename": "DiscussTopicTagNode"
            },
            {
                "id": "45",
                "name": "dynamic programming",
                "slug": "dynamic-programming",
                "numTopics": 1,
                "__typename": "DiscussTopicTagNode"
            },
            {
                "id": "7253",
                "name": "easy-to-understand",
                "slug": "easy-to-understand",
                "numTopics": 1,
                "__typename": "DiscussTopicTagNode"
            },
            {
                "id": "7986",
                "name": "explained",
                "slug": "explained",
                "numTopics": 1,
                "__typename": "DiscussTopicTagNode"
            },
            {
                "id": "12596",
                "name": "explained solution",
                "slug": "explained-solution",
                "numTopics": 1,
                "__typename": "DiscussTopicTagNode"
            },
            {
                "id": "7161",
                "name": "explanation",
                "slug": "explanation",
                "numTopics": 1,
                "__typename": "DiscussTopicTagNode"
            },
            {
                "id": "12066",
                "name": "explanation of logic",
                "slug": "explanation-of-logic",
                "numTopics": 1,
                "__typename": "DiscussTopicTagNode"
            },
            {
                "id": "6793",
                "name": "fast and simple",
                "slug": "fast-and-simple",
                "numTopics": 1,
                "__typename": "DiscussTopicTagNode"
            },
            {
                "id": "7928",
                "name": "go",
                "slug": "go",
                "numTopics": 1,
                "__typename": "DiscussTopicTagNode"
            },
            {
                "id": "335",
                "name": "golang",
                "slug": "golang",
                "numTopics": 1,
                "__typename": "DiscussTopicTagNode"
            },
            {
                "id": "9485",
                "name": "greedy approach",
                "slug": "greedy-approach",
                "numTopics": 1,
                "__typename": "DiscussTopicTagNode"
            },
            {
                "id": "11322",
                "name": "health",
                "slug": "health",
                "numTopics": 1,
                "__typename": "DiscussTopicTagNode"
            },
            {
                "id": "8467",
                "name": "linear time",
                "slug": "linear-time-2",
                "numTopics": 1,
                "__typename": "DiscussTopicTagNode"
            },
            {
                "id": "325",
                "name": "linear-time",
                "slug": "linear-time",
                "numTopics": 1,
                "__typename": "DiscussTopicTagNode"
            },
            {
                "id": "11519",
                "name": "logic",
                "slug": "logic",
                "numTopics": 1,
                "__typename": "DiscussTopicTagNode"
            },
            {
                "id": "6664",
                "name": "prefix sum",
                "slug": "prefix-sum",
                "numTopics": 1,
                "__typename": "DiscussTopicTagNode"
            },
            {
                "id": "8214",
                "name": "python 3",
                "slug": "python-3",
                "numTopics": 1,
                "__typename": "DiscussTopicTagNode"
            },
            {
                "id": "13846",
                "name": "python3.8",
                "slug": "python38",
                "numTopics": 1,
                "__typename": "DiscussTopicTagNode"
            },
            {
                "id": "15457",
                "name": "python3.9",
                "slug": "python39",
                "numTopics": 1,
                "__typename": "DiscussTopicTagNode"
            },
            {
                "id": "382",
                "name": "ruby",
                "slug": "ruby",
                "numTopics": 1,
                "__typename": "DiscussTopicTagNode"
            },
            {
                "id": "6081",
                "name": "simple",
                "slug": "simple",
                "numTopics": 1,
                "__typename": "DiscussTopicTagNode"
            },
            {
                "id": "9026",
                "name": "slide window",
                "slug": "slide-window",
                "numTopics": 1,
                "__typename": "DiscussTopicTagNode"
            },
            {
                "id": "6602",
                "name": "sliding",
                "slug": "sliding",
                "numTopics": 1,
                "__typename": "DiscussTopicTagNode"
            },
            {
                "id": "8398",
                "name": "sliding window algorithm",
                "slug": "sliding-window-algorithm",
                "numTopics": 1,
                "__typename": "DiscussTopicTagNode"
            },
            {
                "id": "6767",
                "name": "sliding-window",
                "slug": "sliding-window",
                "numTopics": 1,
                "__typename": "DiscussTopicTagNode"
            },
            {
                "id": "7163",
                "name": "testcase",
                "slug": "testcase",
                "numTopics": 1,
                "__typename": "DiscussTopicTagNode"
            },
            {
                "id": "14376",
                "name": "ting",
                "slug": "ting",
                "numTopics": 1,
                "__typename": "DiscussTopicTagNode"
            },
            {
                "id": "7827",
                "name": "tle",
                "slug": "tle",
                "numTopics": 1,
                "__typename": "DiscussTopicTagNode"
            },
            {
                "id": "6487",
                "name": "with-explanation",
                "slug": "with-explanation",
                "numTopics": 1,
                "__typename": "DiscussTopicTagNode"
            },
            {
                "id": "7308",
                "name": "xor",
                "slug": "xor",
                "numTopics": 1,
                "__typename": "DiscussTopicTagNode"
            },
            {
                "id": "18248",
                "name": "yakuza",
                "slug": "yakuza",
                "numTopics": 1,
                "__typename": "DiscussTopicTagNode"
            }
        ]
    }
}