{
    "data": {
        "discussQuestionTopicTags": [
            {
                "id": "123",
                "name": "c++",
                "slug": "c",
                "numTopics": 68,
                "__typename": "DiscussTopicTagNode"
            },
            {
                "id": "135",
                "name": "java",
                "slug": "java",
                "numTopics": 57,
                "__typename": "DiscussTopicTagNode"
            },
            {
                "id": "34",
                "name": "python",
                "slug": "python",
                "numTopics": 47,
                "__typename": "DiscussTopicTagNode"
            },
            {
                "id": "98",
                "name": "javascript",
                "slug": "javascript",
                "numTopics": 40,
                "__typename": "DiscussTopicTagNode"
            },
            {
                "id": "415",
                "name": "easy",
                "slug": "easy",
                "numTopics": 26,
                "__typename": "DiscussTopicTagNode"
            },
            {
                "id": "200",
                "name": "cpp",
                "slug": "cpp",
                "numTopics": 25,
                "__typename": "DiscussTopicTagNode"
            },
            {
                "id": "8214",
                "name": "python 3",
                "slug": "python-3",
                "numTopics": 25,
                "__typename": "DiscussTopicTagNode"
            },
            {
                "id": "6167",
                "name": "easy-understanding",
                "slug": "easy-understanding",
                "numTopics": 22,
                "__typename": "DiscussTopicTagNode"
            },
            {
                "id": "6698",
                "name": "python3",
                "slug": "python3",
                "numTopics": 22,
                "__typename": "DiscussTopicTagNode"
            },
            {
                "id": "14",
                "name": "java-solution",
                "slug": "java-solution",
                "numTopics": 21,
                "__typename": "DiscussTopicTagNode"
            },
            {
                "id": "10497",
                "name": "javascript solution",
                "slug": "javascript-solution",
                "numTopics": 13,
                "__typename": "DiscussTopicTagNode"
            },
            {
                "id": "6081",
                "name": "simple",
                "slug": "simple",
                "numTopics": 13,
                "__typename": "DiscussTopicTagNode"
            },
            {
                "id": "6145",
                "name": "one-liner",
                "slug": "one-liner",
                "numTopics": 12,
                "__typename": "DiscussTopicTagNode"
            },
            {
                "id": "346",
                "name": "swift",
                "slug": "swift",
                "numTopics": 11,
                "__typename": "DiscussTopicTagNode"
            },
            {
                "id": "564",
                "name": "c#",
                "slug": "c-2",
                "numTopics": 10,
                "__typename": "DiscussTopicTagNode"
            },
            {
                "id": "6434",
                "name": "one line",
                "slug": "one-line-2",
                "numTopics": 7,
                "__typename": "DiscussTopicTagNode"
            },
            {
                "id": "130",
                "name": "array",
                "slug": "array",
                "numTopics": 6,
                "__typename": "DiscussTopicTagNode"
            },
            {
                "id": "6404",
                "name": "clean code",
                "slug": "clean-code",
                "numTopics": 6,
                "__typename": "DiscussTopicTagNode"
            },
            {
                "id": "6590",
                "name": "fast",
                "slug": "fast",
                "numTopics": 6,
                "__typename": "DiscussTopicTagNode"
            },
            {
                "id": "7226",
                "name": "kotlin",
                "slug": "kotlin",
                "numTopics": 6,
                "__typename": "DiscussTopicTagNode"
            },
            {
                "id": "7934",
                "name": "c",
                "slug": "c-3",
                "numTopics": 5,
                "__typename": "DiscussTopicTagNode"
            },
            {
                "id": "7253",
                "name": "easy-to-understand",
                "slug": "easy-to-understand",
                "numTopics": 5,
                "__typename": "DiscussTopicTagNode"
            },
            {
                "id": "543",
                "name": "scala",
                "slug": "scala",
                "numTopics": 5,
                "__typename": "DiscussTopicTagNode"
            },
            {
                "id": "6265",
                "name": "stl",
                "slug": "stl",
                "numTopics": 5,
                "__typename": "DiscussTopicTagNode"
            },
            {
                "id": "6405",
                "name": "0ms",
                "slug": "0ms",
                "numTopics": 4,
                "__typename": "DiscussTopicTagNode"
            },
            {
                "id": "10496",
                "name": "cpp solution",
                "slug": "cpp-solution-2",
                "numTopics": 4,
                "__typename": "DiscussTopicTagNode"
            },
            {
                "id": "7008",
                "name": "max",
                "slug": "max",
                "numTopics": 4,
                "__typename": "DiscussTopicTagNode"
            },
            {
                "id": "351",
                "name": "solution",
                "slug": "solution",
                "numTopics": 4,
                "__typename": "DiscussTopicTagNode"
            },
            {
                "id": "22",
                "name": "c code",
                "slug": "c-code",
                "numTopics": 3,
                "__typename": "DiscussTopicTagNode"
            },
            {
                "id": "7219",
                "name": "easytounderstand",
                "slug": "easytounderstand",
                "numTopics": 3,
                "__typename": "DiscussTopicTagNode"
            },
            {
                "id": "6426",
                "name": "fast-solution",
                "slug": "fast-solution",
                "numTopics": 3,
                "__typename": "DiscussTopicTagNode"
            },
            {
                "id": "8153",
                "name": "for loop",
                "slug": "for-loop-2",
                "numTopics": 3,
                "__typename": "DiscussTopicTagNode"
            },
            {
                "id": "335",
                "name": "golang",
                "slug": "golang",
                "numTopics": 3,
                "__typename": "DiscussTopicTagNode"
            },
            {
                "id": "7643",
                "name": "loop",
                "slug": "loop",
                "numTopics": 3,
                "__typename": "DiscussTopicTagNode"
            },
            {
                "id": "13846",
                "name": "python3.8",
                "slug": "python38",
                "numTopics": 3,
                "__typename": "DiscussTopicTagNode"
            },
            {
                "id": "7262",
                "name": "reduce",
                "slug": "reduce",
                "numTopics": 3,
                "__typename": "DiscussTopicTagNode"
            },
            {
                "id": "11840",
                "name": "swift5",
                "slug": "swift5",
                "numTopics": 3,
                "__typename": "DiscussTopicTagNode"
            },
            {
                "id": "6699",
                "name": "vector",
                "slug": "vector",
                "numTopics": 3,
                "__typename": "DiscussTopicTagNode"
            },
            {
                "id": "15269",
                "name": "#list comprehension",
                "slug": "list-comprehension-3",
                "numTopics": 2,
                "__typename": "DiscussTopicTagNode"
            },
            {
                "id": "8046",
                "name": "#python",
                "slug": "python-2",
                "numTopics": 2,
                "__typename": "DiscussTopicTagNode"
            },
            {
                "id": "8102",
                "name": "1 line",
                "slug": "1-line-2",
                "numTopics": 2,
                "__typename": "DiscussTopicTagNode"
            },
            {
                "id": "541",
                "name": "2d-array",
                "slug": "2d-array",
                "numTopics": 2,
                "__typename": "DiscussTopicTagNode"
            },
            {
                "id": "6068",
                "name": "accumulate",
                "slug": "accumulate",
                "numTopics": 2,
                "__typename": "DiscussTopicTagNode"
            },
            {
                "id": "12547",
                "name": "beginner friendly",
                "slug": "beginner-friendly",
                "numTopics": 2,
                "__typename": "DiscussTopicTagNode"
            },
            {
                "id": "8176",
                "name": "c++ solution",
                "slug": "c-solution-2",
                "numTopics": 2,
                "__typename": "DiscussTopicTagNode"
            },
            {
                "id": "14101",
                "name": "comments-added",
                "slug": "comments-added-2",
                "numTopics": 2,
                "__typename": "DiscussTopicTagNode"
            },
            {
                "id": "45",
                "name": "dynamic programming",
                "slug": "dynamic-programming",
                "numTopics": 2,
                "__typename": "DiscussTopicTagNode"
            },
            {
                "id": "7098",
                "name": "easiest",
                "slug": "easiest",
                "numTopics": 2,
                "__typename": "DiscussTopicTagNode"
            },
            {
                "id": "7576",
                "name": "es6",
                "slug": "es6",
                "numTopics": 2,
                "__typename": "DiscussTopicTagNode"
            },
            {
                "id": "6793",
                "name": "fast and simple",
                "slug": "fast-and-simple",
                "numTopics": 2,
                "__typename": "DiscussTopicTagNode"
            },
            {
                "id": "8518",
                "name": "faster",
                "slug": "faster",
                "numTopics": 2,
                "__typename": "DiscussTopicTagNode"
            },
            {
                "id": "8793",
                "name": "faster than 100",
                "slug": "faster-than-100",
                "numTopics": 2,
                "__typename": "DiscussTopicTagNode"
            },
            {
                "id": "8423",
                "name": "fasterthan100",
                "slug": "fasterthan100",
                "numTopics": 2,
                "__typename": "DiscussTopicTagNode"
            },
            {
                "id": "7326",
                "name": "fastest",
                "slug": "fastest",
                "numTopics": 2,
                "__typename": "DiscussTopicTagNode"
            },
            {
                "id": "10585",
                "name": "for loops",
                "slug": "for-loops",
                "numTopics": 2,
                "__typename": "DiscussTopicTagNode"
            },
            {
                "id": "15497",
                "name": "javsacript",
                "slug": "javsacript",
                "numTopics": 2,
                "__typename": "DiscussTopicTagNode"
            },
            {
                "id": "7381",
                "name": "linq",
                "slug": "linq",
                "numTopics": 2,
                "__typename": "DiscussTopicTagNode"
            },
            {
                "id": "208",
                "name": "map",
                "slug": "map",
                "numTopics": 2,
                "__typename": "DiscussTopicTagNode"
            },
            {
                "id": "79",
                "name": "matrix",
                "slug": "matrix",
                "numTopics": 2,
                "__typename": "DiscussTopicTagNode"
            },
            {
                "id": "371",
                "name": "numpy",
                "slug": "numpy",
                "numTopics": 2,
                "__typename": "DiscussTopicTagNode"
            },
            {
                "id": "14622",
                "name": "readable code",
                "slug": "readable-code",
                "numTopics": 2,
                "__typename": "DiscussTopicTagNode"
            },
            {
                "id": "18336",
                "name": "richest customer wealth",
                "slug": "richest-customer-wealth",
                "numTopics": 2,
                "__typename": "DiscussTopicTagNode"
            },
            {
                "id": "382",
                "name": "ruby",
                "slug": "ruby",
                "numTopics": 2,
                "__typename": "DiscussTopicTagNode"
            },
            {
                "id": "7898",
                "name": "rust",
                "slug": "rust",
                "numTopics": 2,
                "__typename": "DiscussTopicTagNode"
            },
            {
                "id": "7551",
                "name": "simple python solution",
                "slug": "simple-python-solution",
                "numTopics": 2,
                "__typename": "DiscussTopicTagNode"
            },
            {
                "id": "7433",
                "name": "straight-forward",
                "slug": "straight-forward",
                "numTopics": 2,
                "__typename": "DiscussTopicTagNode"
            },
            {
                "id": "8677",
                "name": "#easy",
                "slug": "easy-2",
                "numTopics": 1,
                "__typename": "DiscussTopicTagNode"
            },
            {
                "id": "8244",
                "name": "#iterator",
                "slug": "iterator-2",
                "numTopics": 1,
                "__typename": "DiscussTopicTagNode"
            },
            {
                "id": "10030",
                "name": "#python 3",
                "slug": "python-3-2",
                "numTopics": 1,
                "__typename": "DiscussTopicTagNode"
            },
            {
                "id": "12346",
                "name": "0ms runtime",
                "slug": "0ms-runtime",
                "numTopics": 1,
                "__typename": "DiscussTopicTagNode"
            },
            {
                "id": "8653",
                "name": "0ms-solution",
                "slug": "0ms-solution",
                "numTopics": 1,
                "__typename": "DiscussTopicTagNode"
            },
            {
                "id": "6682",
                "name": "1-line",
                "slug": "1-line",
                "numTopics": 1,
                "__typename": "DiscussTopicTagNode"
            },
            {
                "id": "12505",
                "name": "1-line solution",
                "slug": "1-line-solution",
                "numTopics": 1,
                "__typename": "DiscussTopicTagNode"
            },
            {
                "id": "6417",
                "name": "100",
                "slug": "100",
                "numTopics": 1,
                "__typename": "DiscussTopicTagNode"
            },
            {
                "id": "8980",
                "name": "100 faster",
                "slug": "100-faster",
                "numTopics": 1,
                "__typename": "DiscussTopicTagNode"
            },
            {
                "id": "6241",
                "name": "4ms",
                "slug": "4ms",
                "numTopics": 1,
                "__typename": "DiscussTopicTagNode"
            },
            {
                "id": "8658",
                "name": "9 lines",
                "slug": "9-lines",
                "numTopics": 1,
                "__typename": "DiscussTopicTagNode"
            },
            {
                "id": "168",
                "name": "arrays",
                "slug": "arrays",
                "numTopics": 1,
                "__typename": "DiscussTopicTagNode"
            },
            {
                "id": "16623",
                "name": "asahiocean",
                "slug": "asahiocean",
                "numTopics": 1,
                "__typename": "DiscussTopicTagNode"
            },
            {
                "id": "8721",
                "name": "basic",
                "slug": "basic",
                "numTopics": 1,
                "__typename": "DiscussTopicTagNode"
            },
            {
                "id": "7091",
                "name": "beginner",
                "slug": "beginner",
                "numTopics": 1,
                "__typename": "DiscussTopicTagNode"
            },
            {
                "id": "8791",
                "name": "beginnerfriendly",
                "slug": "beginnerfriendly",
                "numTopics": 1,
                "__typename": "DiscussTopicTagNode"
            },
            {
                "id": "13931",
                "name": "beginners level",
                "slug": "beginners-level",
                "numTopics": 1,
                "__typename": "DiscussTopicTagNode"
            },
            {
                "id": "6783",
                "name": "best",
                "slug": "best",
                "numTopics": 1,
                "__typename": "DiscussTopicTagNode"
            },
            {
                "id": "10503",
                "name": "best-solution-ever",
                "slug": "best-solution-ever",
                "numTopics": 1,
                "__typename": "DiscussTopicTagNode"
            },
            {
                "id": "7434",
                "name": "brute force",
                "slug": "brute-force-2",
                "numTopics": 1,
                "__typename": "DiscussTopicTagNode"
            },
            {
                "id": "6760",
                "name": "brute-force",
                "slug": "brute-force",
                "numTopics": 1,
                "__typename": "DiscussTopicTagNode"
            },
            {
                "id": "12562",
                "name": "built-in-function",
                "slug": "built-in-function",
                "numTopics": 1,
                "__typename": "DiscussTopicTagNode"
            },
            {
                "id": "5982",
                "name": "c solution",
                "slug": "c-solution",
                "numTopics": 1,
                "__typename": "DiscussTopicTagNode"
            },
            {
                "id": "14144",
                "name": "c#-solution",
                "slug": "c-solution-5",
                "numTopics": 1,
                "__typename": "DiscussTopicTagNode"
            },
            {
                "id": "8973",
                "name": "c++ code",
                "slug": "c-code-2",
                "numTopics": 1,
                "__typename": "DiscussTopicTagNode"
            },
            {
                "id": "11318",
                "name": "c++ easy to understand",
                "slug": "c-easy-to-understand",
                "numTopics": 1,
                "__typename": "DiscussTopicTagNode"
            },
            {
                "id": "6055",
                "name": "clean",
                "slug": "clean",
                "numTopics": 1,
                "__typename": "DiscussTopicTagNode"
            },
            {
                "id": "6481",
                "name": "concise",
                "slug": "concise",
                "numTopics": 1,
                "__typename": "DiscussTopicTagNode"
            },
            {
                "id": "5915",
                "name": "constant time",
                "slug": "constant-time",
                "numTopics": 1,
                "__typename": "DiscussTopicTagNode"
            },
            {
                "id": "359",
                "name": "contest",
                "slug": "contest",
                "numTopics": 1,
                "__typename": "DiscussTopicTagNode"
            },
            {
                "id": "15390",
                "name": "dichotomy",
                "slug": "dichotomy",
                "numTopics": 1,
                "__typename": "DiscussTopicTagNode"
            },
            {
                "id": "18334",
                "name": "easy python solution",
                "slug": "easy-python-solution",
                "numTopics": 1,
                "__typename": "DiscussTopicTagNode"
            },
            {
                "id": "10590",
                "name": "easy solution",
                "slug": "easy-solution-2",
                "numTopics": 1,
                "__typename": "DiscussTopicTagNode"
            },
            {
                "id": "15684",
                "name": "easy to undersstand",
                "slug": "easy-to-undersstand",
                "numTopics": 1,
                "__typename": "DiscussTopicTagNode"
            },
            {
                "id": "9051",
                "name": "easy-to-read",
                "slug": "easy-to-read-2",
                "numTopics": 1,
                "__typename": "DiscussTopicTagNode"
            },
            {
                "id": "6750",
                "name": "efficient",
                "slug": "efficient",
                "numTopics": 1,
                "__typename": "DiscussTopicTagNode"
            },
            {
                "id": "11181",
                "name": "esy sol",
                "slug": "esy-sol",
                "numTopics": 1,
                "__typename": "DiscussTopicTagNode"
            },
            {
                "id": "7986",
                "name": "explained",
                "slug": "explained",
                "numTopics": 1,
                "__typename": "DiscussTopicTagNode"
            },
            {
                "id": "7161",
                "name": "explanation",
                "slug": "explanation",
                "numTopics": 1,
                "__typename": "DiscussTopicTagNode"
            },
            {
                "id": "12066",
                "name": "explanation of logic",
                "slug": "explanation-of-logic",
                "numTopics": 1,
                "__typename": "DiscussTopicTagNode"
            },
            {
                "id": "6150",
                "name": "functional",
                "slug": "functional",
                "numTopics": 1,
                "__typename": "DiscussTopicTagNode"
            },
            {
                "id": "11809",
                "name": "generator expression",
                "slug": "generator-expression-2",
                "numTopics": 1,
                "__typename": "DiscussTopicTagNode"
            },
            {
                "id": "5943",
                "name": "go-solution",
                "slug": "go-solution",
                "numTopics": 1,
                "__typename": "DiscussTopicTagNode"
            },
            {
                "id": "6607",
                "name": "golang-solution",
                "slug": "golang-solution",
                "numTopics": 1,
                "__typename": "DiscussTopicTagNode"
            },
            {
                "id": "40",
                "name": "grid",
                "slug": "grid",
                "numTopics": 1,
                "__typename": "DiscussTopicTagNode"
            },
            {
                "id": "8704",
                "name": "higher order functions",
                "slug": "higher-order-functions",
                "numTopics": 1,
                "__typename": "DiscussTopicTagNode"
            },
            {
                "id": "16883",
                "name": "implicit return",
                "slug": "implicit-return",
                "numTopics": 1,
                "__typename": "DiscussTopicTagNode"
            },
            {
                "id": "6187",
                "name": "indent",
                "slug": "indent",
                "numTopics": 1,
                "__typename": "DiscussTopicTagNode"
            },
            {
                "id": "10360",
                "name": "intutive",
                "slug": "intutive",
                "numTopics": 1,
                "__typename": "DiscussTopicTagNode"
            },
            {
                "id": "11023",
                "name": "iterate",
                "slug": "iterate",
                "numTopics": 1,
                "__typename": "DiscussTopicTagNode"
            },
            {
                "id": "111",
                "name": "iterative",
                "slug": "iterative",
                "numTopics": 1,
                "__typename": "DiscussTopicTagNode"
            },
            {
                "id": "16555",
                "name": "izaac",
                "slug": "izaac",
                "numTopics": 1,
                "__typename": "DiscussTopicTagNode"
            },
            {
                "id": "5889",
                "name": "java ac solution",
                "slug": "java-ac-solution",
                "numTopics": 1,
                "__typename": "DiscussTopicTagNode"
            },
            {
                "id": "5997",
                "name": "javacript",
                "slug": "javacript",
                "numTopics": 1,
                "__typename": "DiscussTopicTagNode"
            },
            {
                "id": "15063",
                "name": "javascript arrays",
                "slug": "javascript-arrays",
                "numTopics": 1,
                "__typename": "DiscussTopicTagNode"
            },
            {
                "id": "9296",
                "name": "javascriptes6",
                "slug": "javascriptes6",
                "numTopics": 1,
                "__typename": "DiscussTopicTagNode"
            },
            {
                "id": "7893",
                "name": "js",
                "slug": "js",
                "numTopics": 1,
                "__typename": "DiscussTopicTagNode"
            },
            {
                "id": "14023",
                "name": "kotlin-solution",
                "slug": "kotlin-solution",
                "numTopics": 1,
                "__typename": "DiscussTopicTagNode"
            },
            {
                "id": "53",
                "name": "list",
                "slug": "list",
                "numTopics": 1,
                "__typename": "DiscussTopicTagNode"
            },
            {
                "id": "5851",
                "name": "list comprehension",
                "slug": "list-comprehension",
                "numTopics": 1,
                "__typename": "DiscussTopicTagNode"
            },
            {
                "id": "7542",
                "name": "loops",
                "slug": "loops",
                "numTopics": 1,
                "__typename": "DiscussTopicTagNode"
            },
            {
                "id": "54",
                "name": "mapreduce",
                "slug": "mapreduce",
                "numTopics": 1,
                "__typename": "DiscussTopicTagNode"
            },
            {
                "id": "71",
                "name": "maximum",
                "slug": "maximum",
                "numTopics": 1,
                "__typename": "DiscussTopicTagNode"
            },
            {
                "id": "8412",
                "name": "memory efficient",
                "slug": "memory-efficient",
                "numTopics": 1,
                "__typename": "DiscussTopicTagNode"
            },
            {
                "id": "17404",
                "name": "multidimentional array",
                "slug": "multidimentional-array",
                "numTopics": 1,
                "__typename": "DiscussTopicTagNode"
            },
            {
                "id": "15503",
                "name": "negative infinity",
                "slug": "negative-infinity",
                "numTopics": 1,
                "__typename": "DiscussTopicTagNode"
            },
            {
                "id": "6693",
                "name": "o1 space",
                "slug": "o1-space",
                "numTopics": 1,
                "__typename": "DiscussTopicTagNode"
            },
            {
                "id": "6255",
                "name": "one-line",
                "slug": "one-line",
                "numTopics": 1,
                "__typename": "DiscussTopicTagNode"
            },
            {
                "id": "5956",
                "name": "oneline",
                "slug": "oneline",
                "numTopics": 1,
                "__typename": "DiscussTopicTagNode"
            },
            {
                "id": "7688",
                "name": "optimized",
                "slug": "optimized",
                "numTopics": 1,
                "__typename": "DiscussTopicTagNode"
            },
            {
                "id": "324",
                "name": "php",
                "slug": "php",
                "numTopics": 1,
                "__typename": "DiscussTopicTagNode"
            },
            {
                "id": "6989",
                "name": "priority queue",
                "slug": "priority-queue-2",
                "numTopics": 1,
                "__typename": "DiscussTopicTagNode"
            },
            {
                "id": "11984",
                "name": "python easy",
                "slug": "python-easy-2",
                "numTopics": 1,
                "__typename": "DiscussTopicTagNode"
            },
            {
                "id": "16683",
                "name": "python simple",
                "slug": "python-simple",
                "numTopics": 1,
                "__typename": "DiscussTopicTagNode"
            },
            {
                "id": "12317",
                "name": "question need help",
                "slug": "question-need-help",
                "numTopics": 1,
                "__typename": "DiscussTopicTagNode"
            },
            {
                "id": "6754",
                "name": "readable",
                "slug": "readable",
                "numTopics": 1,
                "__typename": "DiscussTopicTagNode"
            },
            {
                "id": "199",
                "name": "recursion",
                "slug": "recursion",
                "numTopics": 1,
                "__typename": "DiscussTopicTagNode"
            },
            {
                "id": "228",
                "name": "recursive",
                "slug": "recursive",
                "numTopics": 1,
                "__typename": "DiscussTopicTagNode"
            },
            {
                "id": "16007",
                "name": "rescursive",
                "slug": "rescursive",
                "numTopics": 1,
                "__typename": "DiscussTopicTagNode"
            },
            {
                "id": "8785",
                "name": "self-explanatory",
                "slug": "self-explanatory",
                "numTopics": 1,
                "__typename": "DiscussTopicTagNode"
            },
            {
                "id": "6868",
                "name": "short",
                "slug": "short",
                "numTopics": 1,
                "__typename": "DiscussTopicTagNode"
            },
            {
                "id": "8166",
                "name": "simple java solution",
                "slug": "simple-java-solution",
                "numTopics": 1,
                "__typename": "DiscussTopicTagNode"
            },
            {
                "id": "8215",
                "name": "solution-javascript",
                "slug": "solution-javascript",
                "numTopics": 1,
                "__typename": "DiscussTopicTagNode"
            },
            {
                "id": "12018",
                "name": "space complexity",
                "slug": "space-complexity-2",
                "numTopics": 1,
                "__typename": "DiscussTopicTagNode"
            },
            {
                "id": "7501",
                "name": "std",
                "slug": "std",
                "numTopics": 1,
                "__typename": "DiscussTopicTagNode"
            },
            {
                "id": "8418",
                "name": "stl algorithms",
                "slug": "stl-algorithms",
                "numTopics": 1,
                "__typename": "DiscussTopicTagNode"
            },
            {
                "id": "6430",
                "name": "straightforward",
                "slug": "straightforward",
                "numTopics": 1,
                "__typename": "DiscussTopicTagNode"
            },
            {
                "id": "7868",
                "name": "stream",
                "slug": "stream",
                "numTopics": 1,
                "__typename": "DiscussTopicTagNode"
            },
            {
                "id": "7811",
                "name": "sum",
                "slug": "sum",
                "numTopics": 1,
                "__typename": "DiscussTopicTagNode"
            },
            {
                "id": "8090",
                "name": "time complexity",
                "slug": "time-complexity-2",
                "numTopics": 1,
                "__typename": "DiscussTopicTagNode"
            },
            {
                "id": "6932",
                "name": "time-complexity-o",
                "slug": "time-complexity-o",
                "numTopics": 1,
                "__typename": "DiscussTopicTagNode"
            },
            {
                "id": "8555",
                "name": "typescript",
                "slug": "typescript",
                "numTopics": 1,
                "__typename": "DiscussTopicTagNode"
            },
            {
                "id": "11466",
                "name": "ultra easy",
                "slug": "ultra-easy",
                "numTopics": 1,
                "__typename": "DiscussTopicTagNode"
            },
            {
                "id": "8774",
                "name": "understandable",
                "slug": "understandable",
                "numTopics": 1,
                "__typename": "DiscussTopicTagNode"
            },
            {
                "id": "9752",
                "name": "upvote",
                "slug": "upvote",
                "numTopics": 1,
                "__typename": "DiscussTopicTagNode"
            },
            {
                "id": "13452",
                "name": "vector 2d",
                "slug": "vector-2d",
                "numTopics": 1,
                "__typename": "DiscussTopicTagNode"
            }
        ]
    }
}