{
    "data": {
        "topic": {
            "id": 127437,
            "viewCount": 18517,
            "topLevelCommentCount": 16,
            "subscribed": false,
            "title": "Binary Trees With Factors",
            "pinned": false,
            "tags": [],
            "hideFromTrending": false,
            "post": {
                "id": 255652,
                "voteCount": 0,
                "voteStatus": 0,
                "content": "---\\n\\n**Click [here](https://leetcode.com/articles/binary-trees-with-factors) to see the full article post**",
                "updationDate": 1524364978,
                "creationDate": 1524364978,
                "status": null,
                "isHidden": null,
                "coinRewards": [],
                "author": {
                    "isDiscussAdmin": false,
                    "isDiscussStaff": false,
                    "username": "awice",
                    "nameColor": null,
                    "activeBadge": null,
                    "profile": {
                        "userAvatar": "https://assets.leetcode.com/users/awice/avatar_1576905115.png",
                        "reputation": 6689,
                        "__typename": "UserProfileNode"
                    },
                    "isActive": true,
                    "__typename": "UserNode"
                },
                "authorIsModerator": false,
                "isOwnPost": false,
                "__typename": "PostNode"
            },
            "__typename": "TopicNode"
        }
    }
}