{
    "data": {
        "discussQuestionTopicTags": [
            {
                "id": "123",
                "name": "c++",
                "slug": "c",
                "numTopics": 5,
                "__typename": "DiscussTopicTagNode"
            },
            {
                "id": "135",
                "name": "java",
                "slug": "java",
                "numTopics": 4,
                "__typename": "DiscussTopicTagNode"
            },
            {
                "id": "6167",
                "name": "easy-understanding",
                "slug": "easy-understanding",
                "numTopics": 2,
                "__typename": "DiscussTopicTagNode"
            },
            {
                "id": "34",
                "name": "python",
                "slug": "python",
                "numTopics": 2,
                "__typename": "DiscussTopicTagNode"
            },
            {
                "id": "6698",
                "name": "python3",
                "slug": "python3",
                "numTopics": 2,
                "__typename": "DiscussTopicTagNode"
            },
            {
                "id": "130",
                "name": "array",
                "slug": "array",
                "numTopics": 1,
                "__typename": "DiscussTopicTagNode"
            },
            {
                "id": "8973",
                "name": "c++ code",
                "slug": "c-code-2",
                "numTopics": 1,
                "__typename": "DiscussTopicTagNode"
            },
            {
                "id": "7930",
                "name": "c++17",
                "slug": "c17",
                "numTopics": 1,
                "__typename": "DiscussTopicTagNode"
            },
            {
                "id": "6404",
                "name": "clean code",
                "slug": "clean-code",
                "numTopics": 1,
                "__typename": "DiscussTopicTagNode"
            },
            {
                "id": "8276",
                "name": "cleanest",
                "slug": "cleanest",
                "numTopics": 1,
                "__typename": "DiscussTopicTagNode"
            },
            {
                "id": "6481",
                "name": "concise",
                "slug": "concise",
                "numTopics": 1,
                "__typename": "DiscussTopicTagNode"
            },
            {
                "id": "200",
                "name": "cpp",
                "slug": "cpp",
                "numTopics": 1,
                "__typename": "DiscussTopicTagNode"
            },
            {
                "id": "415",
                "name": "easy",
                "slug": "easy",
                "numTopics": 1,
                "__typename": "DiscussTopicTagNode"
            },
            {
                "id": "7219",
                "name": "easytounderstand",
                "slug": "easytounderstand",
                "numTopics": 1,
                "__typename": "DiscussTopicTagNode"
            },
            {
                "id": "16505",
                "name": "fuck noobs",
                "slug": "fuck-noobs",
                "numTopics": 1,
                "__typename": "DiscussTopicTagNode"
            },
            {
                "id": "15699",
                "name": "intiution",
                "slug": "intiution",
                "numTopics": 1,
                "__typename": "DiscussTopicTagNode"
            },
            {
                "id": "98",
                "name": "javascript",
                "slug": "javascript",
                "numTopics": 1,
                "__typename": "DiscussTopicTagNode"
            },
            {
                "id": "12058",
                "name": "lambdas",
                "slug": "lambdas",
                "numTopics": 1,
                "__typename": "DiscussTopicTagNode"
            },
            {
                "id": "8886",
                "name": "mathematics",
                "slug": "mathematics",
                "numTopics": 1,
                "__typename": "DiscussTopicTagNode"
            },
            {
                "id": "8577",
                "name": "maths",
                "slug": "maths",
                "numTopics": 1,
                "__typename": "DiscussTopicTagNode"
            },
            {
                "id": "8214",
                "name": "python 3",
                "slug": "python-3",
                "numTopics": 1,
                "__typename": "DiscussTopicTagNode"
            }
        ]
    }
}