{
    "data": {
        "discussQuestionTopicTags": [
            {
                "id": "34",
                "name": "python",
                "slug": "python",
                "numTopics": 26,
                "__typename": "DiscussTopicTagNode"
            },
            {
                "id": "8214",
                "name": "python 3",
                "slug": "python-3",
                "numTopics": 21,
                "__typename": "DiscussTopicTagNode"
            },
            {
                "id": "123",
                "name": "c++",
                "slug": "c",
                "numTopics": 17,
                "__typename": "DiscussTopicTagNode"
            },
            {
                "id": "135",
                "name": "java",
                "slug": "java",
                "numTopics": 15,
                "__typename": "DiscussTopicTagNode"
            },
            {
                "id": "98",
                "name": "javascript",
                "slug": "javascript",
                "numTopics": 13,
                "__typename": "DiscussTopicTagNode"
            },
            {
                "id": "6698",
                "name": "python3",
                "slug": "python3",
                "numTopics": 12,
                "__typename": "DiscussTopicTagNode"
            },
            {
                "id": "200",
                "name": "cpp",
                "slug": "cpp",
                "numTopics": 11,
                "__typename": "DiscussTopicTagNode"
            },
            {
                "id": "564",
                "name": "c#",
                "slug": "c-2",
                "numTopics": 10,
                "__typename": "DiscussTopicTagNode"
            },
            {
                "id": "415",
                "name": "easy",
                "slug": "easy",
                "numTopics": 6,
                "__typename": "DiscussTopicTagNode"
            },
            {
                "id": "32",
                "name": "string",
                "slug": "string",
                "numTopics": 5,
                "__typename": "DiscussTopicTagNode"
            },
            {
                "id": "6167",
                "name": "easy-understanding",
                "slug": "easy-understanding",
                "numTopics": 4,
                "__typename": "DiscussTopicTagNode"
            },
            {
                "id": "335",
                "name": "golang",
                "slug": "golang",
                "numTopics": 4,
                "__typename": "DiscussTopicTagNode"
            },
            {
                "id": "14",
                "name": "java-solution",
                "slug": "java-solution",
                "numTopics": 4,
                "__typename": "DiscussTopicTagNode"
            },
            {
                "id": "12",
                "name": "string-operation",
                "slug": "string-operation",
                "numTopics": 4,
                "__typename": "DiscussTopicTagNode"
            },
            {
                "id": "7253",
                "name": "easy-to-understand",
                "slug": "easy-to-understand",
                "numTopics": 3,
                "__typename": "DiscussTopicTagNode"
            },
            {
                "id": "6158",
                "name": "solution-sharing-cpp",
                "slug": "solution-sharing-cpp",
                "numTopics": 3,
                "__typename": "DiscussTopicTagNode"
            },
            {
                "id": "16874",
                "name": "#codeboy",
                "slug": "codeboy",
                "numTopics": 2,
                "__typename": "DiscussTopicTagNode"
            },
            {
                "id": "11417",
                "name": "#easy solution",
                "slug": "easy-solution-3",
                "numTopics": 2,
                "__typename": "DiscussTopicTagNode"
            },
            {
                "id": "11779",
                "name": "#easy-understanding",
                "slug": "easy-understanding-3",
                "numTopics": 2,
                "__typename": "DiscussTopicTagNode"
            },
            {
                "id": "8046",
                "name": "#python",
                "slug": "python-2",
                "numTopics": 2,
                "__typename": "DiscussTopicTagNode"
            },
            {
                "id": "10030",
                "name": "#python 3",
                "slug": "python-3-2",
                "numTopics": 2,
                "__typename": "DiscussTopicTagNode"
            },
            {
                "id": "10496",
                "name": "cpp solution",
                "slug": "cpp-solution-2",
                "numTopics": 2,
                "__typename": "DiscussTopicTagNode"
            },
            {
                "id": "353",
                "name": "csharp",
                "slug": "csharp",
                "numTopics": 2,
                "__typename": "DiscussTopicTagNode"
            },
            {
                "id": "9228",
                "name": "easy-undestand",
                "slug": "easy-undestand",
                "numTopics": 2,
                "__typename": "DiscussTopicTagNode"
            },
            {
                "id": "7219",
                "name": "easytounderstand",
                "slug": "easytounderstand",
                "numTopics": 2,
                "__typename": "DiscussTopicTagNode"
            },
            {
                "id": "6472",
                "name": "explaination",
                "slug": "explaination",
                "numTopics": 2,
                "__typename": "DiscussTopicTagNode"
            },
            {
                "id": "5943",
                "name": "go-solution",
                "slug": "go-solution",
                "numTopics": 2,
                "__typename": "DiscussTopicTagNode"
            },
            {
                "id": "6607",
                "name": "golang-solution",
                "slug": "golang-solution",
                "numTopics": 2,
                "__typename": "DiscussTopicTagNode"
            },
            {
                "id": "7059",
                "name": "java solution",
                "slug": "java-solution-2",
                "numTopics": 2,
                "__typename": "DiscussTopicTagNode"
            },
            {
                "id": "53",
                "name": "list",
                "slug": "list",
                "numTopics": 2,
                "__typename": "DiscussTopicTagNode"
            },
            {
                "id": "7186",
                "name": "naive",
                "slug": "naive",
                "numTopics": 2,
                "__typename": "DiscussTopicTagNode"
            },
            {
                "id": "6081",
                "name": "simple",
                "slug": "simple",
                "numTopics": 2,
                "__typename": "DiscussTopicTagNode"
            },
            {
                "id": "8456",
                "name": "simple solution",
                "slug": "simple-solution-2",
                "numTopics": 2,
                "__typename": "DiscussTopicTagNode"
            },
            {
                "id": "351",
                "name": "solution",
                "slug": "solution",
                "numTopics": 2,
                "__typename": "DiscussTopicTagNode"
            },
            {
                "id": "227",
                "name": "stack",
                "slug": "stack",
                "numTopics": 2,
                "__typename": "DiscussTopicTagNode"
            },
            {
                "id": "13839",
                "name": "string builder",
                "slug": "string-builder",
                "numTopics": 2,
                "__typename": "DiscussTopicTagNode"
            },
            {
                "id": "6349",
                "name": "stringbuilder",
                "slug": "stringbuilder",
                "numTopics": 2,
                "__typename": "DiscussTopicTagNode"
            },
            {
                "id": "181",
                "name": "strings",
                "slug": "strings",
                "numTopics": 2,
                "__typename": "DiscussTopicTagNode"
            },
            {
                "id": "346",
                "name": "swift",
                "slug": "swift",
                "numTopics": 2,
                "__typename": "DiscussTopicTagNode"
            },
            {
                "id": "11789",
                "name": "#easysolution",
                "slug": "easysolution",
                "numTopics": 1,
                "__typename": "DiscussTopicTagNode"
            },
            {
                "id": "8184",
                "name": "#java",
                "slug": "java-2",
                "numTopics": 1,
                "__typename": "DiscussTopicTagNode"
            },
            {
                "id": "12810",
                "name": "#string",
                "slug": "string-2",
                "numTopics": 1,
                "__typename": "DiscussTopicTagNode"
            },
            {
                "id": "17977",
                "name": "#stringbuilder",
                "slug": "stringbuilder-2",
                "numTopics": 1,
                "__typename": "DiscussTopicTagNode"
            },
            {
                "id": "8223",
                "name": "algorithms",
                "slug": "algorithms",
                "numTopics": 1,
                "__typename": "DiscussTopicTagNode"
            },
            {
                "id": "16623",
                "name": "asahiocean",
                "slug": "asahiocean",
                "numTopics": 1,
                "__typename": "DiscussTopicTagNode"
            },
            {
                "id": "12547",
                "name": "beginner friendly",
                "slug": "beginner-friendly",
                "numTopics": 1,
                "__typename": "DiscussTopicTagNode"
            },
            {
                "id": "9782",
                "name": "bug-test-case",
                "slug": "bug-test-case",
                "numTopics": 1,
                "__typename": "DiscussTopicTagNode"
            },
            {
                "id": "7934",
                "name": "c",
                "slug": "c-3",
                "numTopics": 1,
                "__typename": "DiscussTopicTagNode"
            },
            {
                "id": "17172",
                "name": "c lang",
                "slug": "c-lang",
                "numTopics": 1,
                "__typename": "DiscussTopicTagNode"
            },
            {
                "id": "14144",
                "name": "c#-solution",
                "slug": "c-solution-5",
                "numTopics": 1,
                "__typename": "DiscussTopicTagNode"
            },
            {
                "id": "11818",
                "name": "chaining",
                "slug": "chaining",
                "numTopics": 1,
                "__typename": "DiscussTopicTagNode"
            },
            {
                "id": "6404",
                "name": "clean code",
                "slug": "clean-code",
                "numTopics": 1,
                "__typename": "DiscussTopicTagNode"
            },
            {
                "id": "12328",
                "name": "cpp soltuion",
                "slug": "cpp-soltuion",
                "numTopics": 1,
                "__typename": "DiscussTopicTagNode"
            },
            {
                "id": "6031",
                "name": "cpp-solution",
                "slug": "cpp-solution",
                "numTopics": 1,
                "__typename": "DiscussTopicTagNode"
            },
            {
                "id": "7576",
                "name": "es6",
                "slug": "es6",
                "numTopics": 1,
                "__typename": "DiscussTopicTagNode"
            },
            {
                "id": "12543",
                "name": "explanatory comments",
                "slug": "explanatory-comments",
                "numTopics": 1,
                "__typename": "DiscussTopicTagNode"
            },
            {
                "id": "6590",
                "name": "fast",
                "slug": "fast",
                "numTopics": 1,
                "__typename": "DiscussTopicTagNode"
            },
            {
                "id": "6793",
                "name": "fast and simple",
                "slug": "fast-and-simple",
                "numTopics": 1,
                "__typename": "DiscussTopicTagNode"
            },
            {
                "id": "6499",
                "name": "for-loop",
                "slug": "for-loop",
                "numTopics": 1,
                "__typename": "DiscussTopicTagNode"
            },
            {
                "id": "8220",
                "name": "functional programming",
                "slug": "functional-programming-2",
                "numTopics": 1,
                "__typename": "DiscussTopicTagNode"
            },
            {
                "id": "7928",
                "name": "go",
                "slug": "go",
                "numTopics": 1,
                "__typename": "DiscussTopicTagNode"
            },
            {
                "id": "12496",
                "name": "good variable names",
                "slug": "good-variable-names-2",
                "numTopics": 1,
                "__typename": "DiscussTopicTagNode"
            },
            {
                "id": "9504",
                "name": "helper",
                "slug": "helper",
                "numTopics": 1,
                "__typename": "DiscussTopicTagNode"
            },
            {
                "id": "9497",
                "name": "insert",
                "slug": "insert",
                "numTopics": 1,
                "__typename": "DiscussTopicTagNode"
            },
            {
                "id": "216",
                "name": "ios",
                "slug": "ios",
                "numTopics": 1,
                "__typename": "DiscussTopicTagNode"
            },
            {
                "id": "6464",
                "name": "javascrip",
                "slug": "javascrip",
                "numTopics": 1,
                "__typename": "DiscussTopicTagNode"
            },
            {
                "id": "10497",
                "name": "javascript solution",
                "slug": "javascript-solution",
                "numTopics": 1,
                "__typename": "DiscussTopicTagNode"
            },
            {
                "id": "6858",
                "name": "join",
                "slug": "join",
                "numTopics": 1,
                "__typename": "DiscussTopicTagNode"
            },
            {
                "id": "7893",
                "name": "js",
                "slug": "js",
                "numTopics": 1,
                "__typename": "DiscussTopicTagNode"
            },
            {
                "id": "17787",
                "name": "leetcode482",
                "slug": "leetcode482",
                "numTopics": 1,
                "__typename": "DiscussTopicTagNode"
            },
            {
                "id": "6686",
                "name": "linear",
                "slug": "linear",
                "numTopics": 1,
                "__typename": "DiscussTopicTagNode"
            },
            {
                "id": "8767",
                "name": "linear space",
                "slug": "linear-space-2",
                "numTopics": 1,
                "__typename": "DiscussTopicTagNode"
            },
            {
                "id": "8467",
                "name": "linear time",
                "slug": "linear-time-2",
                "numTopics": 1,
                "__typename": "DiscussTopicTagNode"
            },
            {
                "id": "6593",
                "name": "one pass",
                "slug": "one-pass-2",
                "numTopics": 1,
                "__typename": "DiscussTopicTagNode"
            },
            {
                "id": "7960",
                "name": "python2",
                "slug": "python2",
                "numTopics": 1,
                "__typename": "DiscussTopicTagNode"
            },
            {
                "id": "296",
                "name": "queue",
                "slug": "queue",
                "numTopics": 1,
                "__typename": "DiscussTopicTagNode"
            },
            {
                "id": "7262",
                "name": "reduce",
                "slug": "reduce",
                "numTopics": 1,
                "__typename": "DiscussTopicTagNode"
            },
            {
                "id": "382",
                "name": "ruby",
                "slug": "ruby",
                "numTopics": 1,
                "__typename": "DiscussTopicTagNode"
            },
            {
                "id": "7898",
                "name": "rust",
                "slug": "rust",
                "numTopics": 1,
                "__typename": "DiscussTopicTagNode"
            },
            {
                "id": "8785",
                "name": "self-explanatory",
                "slug": "self-explanatory",
                "numTopics": 1,
                "__typename": "DiscussTopicTagNode"
            },
            {
                "id": "7166",
                "name": "simple-solution",
                "slug": "simple-solution",
                "numTopics": 1,
                "__typename": "DiscussTopicTagNode"
            },
            {
                "id": "9749",
                "name": "slicing",
                "slug": "slicing",
                "numTopics": 1,
                "__typename": "DiscussTopicTagNode"
            },
            {
                "id": "6909",
                "name": "solution-explaining",
                "slug": "solution-explaining",
                "numTopics": 1,
                "__typename": "DiscussTopicTagNode"
            },
            {
                "id": "5931",
                "name": "split",
                "slug": "split",
                "numTopics": 1,
                "__typename": "DiscussTopicTagNode"
            },
            {
                "id": "8720",
                "name": "stacks",
                "slug": "stacks",
                "numTopics": 1,
                "__typename": "DiscussTopicTagNode"
            },
            {
                "id": "9209",
                "name": "string manipulation",
                "slug": "string-manipulation",
                "numTopics": 1,
                "__typename": "DiscussTopicTagNode"
            },
            {
                "id": "11840",
                "name": "swift5",
                "slug": "swift5",
                "numTopics": 1,
                "__typename": "DiscussTopicTagNode"
            },
            {
                "id": "6915",
                "name": "switch",
                "slug": "switch",
                "numTopics": 1,
                "__typename": "DiscussTopicTagNode"
            },
            {
                "id": "7942",
                "name": "test-cases",
                "slug": "test-cases-2",
                "numTopics": 1,
                "__typename": "DiscussTopicTagNode"
            },
            {
                "id": "6968",
                "name": "wrong-test-cases",
                "slug": "wrong-test-cases",
                "numTopics": 1,
                "__typename": "DiscussTopicTagNode"
            }
        ]
    }
}